guardonce/__init__.py
guardonce/checkguard.py
guardonce/guard2once.py
guardonce/once2guard.py
guardonce/pattern_compiler.py
guardonce/template.py
guardonce/util.py
guardonce-2.4.0.dist-info/LICENSE
guardonce-2.4.0.dist-info/METADATA
guardonce-2.4.0.dist-info/WHEEL
guardonce-2.4.0.dist-info/entry_points.txt
guardonce-2.4.0.dist-info/top_level.txt
guardonce-2.4.0.dist-info/RECORD
